norangTest/test1.py
norangTest/test2.py
norangTest-0.0.0.1.dist-info/METADATA
norangTest-0.0.0.1.dist-info/WHEEL
norangTest-0.0.0.1.dist-info/top_level.txt
norangTest-0.0.0.1.dist-info/RECORD
