Metadata-Version: 2.1
Name: norangTest
Version: 0.0.0.1
Summary: My First Test Package
Home-page: https://lingua.blog.me/…
Author: Yusin Seo
Author-email: yusin0204@naver.com
License: MIT
Requires-Python: >=3
